gigpower/__init__.py
gigpower/bus.py
gigpower/bus_group.py
gigpower/capacitor.py
gigpower/capacitor_group.py
gigpower/circuit.py
gigpower/circuit_element.py
gigpower/circuit_element_group.py
gigpower/line.py
gigpower/line_group.py
gigpower/load.py
gigpower/load_group.py
gigpower/pretty_print.py
gigpower/solution.py
gigpower/solution_dss.py
gigpower/solution_fbs.py
gigpower/solution_nr3.py
gigpower/transformer.py
gigpower/transformer_group.py
gigpower/utils.py
gigpower/volt_var_controller.py
gigpower/voltage_regulator.py
gigpower/voltage_regulator_group.py
gigpower/nr3_lib/__init__.py
gigpower/nr3_lib/compute_NR3FT.py
gigpower/nr3_lib/compute_NR3JT.py
gigpower/nr3_lib/map_output.py
gigpower-1.0.1.dist-info/LICENSE
gigpower-1.0.1.dist-info/METADATA
gigpower-1.0.1.dist-info/WHEEL
gigpower-1.0.1.dist-info/top_level.txt
gigpower-1.0.1.dist-info/RECORD
